debiased_sd/__init__.py
debiased_sd/__main__.py
debiased_sd/estimators.py
debiased_sd/utils.py
debiased_sd-0.1.1.dist-info/AUTHORS.rst
debiased_sd-0.1.1.dist-info/LICENSE
debiased_sd-0.1.1.dist-info/METADATA
debiased_sd-0.1.1.dist-info/WHEEL
debiased_sd-0.1.1.dist-info/top_level.txt
debiased_sd-0.1.1.dist-info/RECORD
