Metadata-Version: 2.1
Name: debiased_sd
Version: 0.1.1
Summary: Package for debiasing the sample SD estimator
Author-email: Erik Drysdale <erikinwest@gmail.com>
Maintainer-email: Erik Drysdale <erikinwest@gmail.com>
License: GNU General Public License v3
Project-URL: bugs, https://github.com/erikinbc/debiased_sd/issues
Project-URL: changelog, https://github.com/erikinbc/debiased_sd/blob/master/changelog.md
Project-URL: homepage, https://github.com/erikinbc/debiased_sd
License-File: LICENSE
License-File: AUTHORS.rst
Provides-Extra: dev
Requires-Dist: coverage ; extra == 'dev'
Requires-Dist: mypy ; extra == 'dev'
Requires-Dist: pytest ; extra == 'dev'
Requires-Dist: ruff ; extra == 'dev'
